whitebox_plugin_device_insta360/pyproject.toml
whitebox_plugin_device_insta360/__init__.py
whitebox_plugin_device_insta360/device_wizards.py
whitebox_plugin_device_insta360/devices.py
whitebox_plugin_device_insta360/external-asset-manifest.json
whitebox_plugin_device_insta360/plugin.py
whitebox_plugin_device_insta360/tasks.py
whitebox_plugin_device_insta360/templates/whitebox_plugin_device_insta360/wizard/intro.html
whitebox_plugin_device_insta360/templates/whitebox_plugin_device_insta360/wizard/step1.html
whitebox_plugin_device_insta360/templates/whitebox_plugin_device_insta360/wizard/step2.html
whitebox_plugin_device_insta360/templates/whitebox_plugin_device_insta360/wizard/step3.html
whitebox_plugin_device_insta360/templates/whitebox_plugin_device_insta360/wizard/step4.html
whitebox_plugin_device_insta360/utils.py
whitebox_plugin_device_insta360/whitebox_plugin_device_insta360.py
whitebox_test_plugin_device_insta360/__init__.py
whitebox_test_plugin_device_insta360/base.py
whitebox_test_plugin_device_insta360/test_device.py
whitebox_test_plugin_device_insta360/test_plugin.py
whitebox_test_plugin_device_insta360/test_tasks.py
whitebox_test_plugin_device_insta360/test_utils.py
whitebox_plugin_device_insta360-0.1.16.dist-info/LICENSE
whitebox_plugin_device_insta360-0.1.16.dist-info/METADATA
whitebox_plugin_device_insta360-0.1.16.dist-info/WHEEL
whitebox_plugin_device_insta360-0.1.16.dist-info/RECORD
