Metadata-Version: 2.3
Name: whitebox-plugin-device-insta360
Version: 0.1.16
Summary: A plugin for whitebox to interface with Insta360 cameras
License: GNU Affero General Public License v3
Author: Milos
Author-email: hello@klined.org
Requires-Python: >=3.10.0
Classifier: License :: Other/Proprietary License
Classifier: Programming Language :: Python :: 3
Classifier: Programming Language :: Python :: 3.10
Classifier: Programming Language :: Python :: 3.11
Classifier: Programming Language :: Python :: 3.12
Classifier: Programming Language :: Python :: 3.13
Requires-Dist: insta360 (>=0.1.11,<0.2.0)
